rendb.py
rendb-2.0.0.dist-info/licenses/LICENSE.txt
rendb-2.0.0.dist-info/METADATA
rendb-2.0.0.dist-info/WHEEL
rendb-2.0.0.dist-info/top_level.txt
rendb-2.0.0.dist-info/RECORD
