Metadata-Version: 2.4
Name: rendb
Version: 2.0.0
Summary: doubao
Author-email: rxy <1302553960@qq.com>
Classifier: Programming Language :: Python :: 3
Classifier: License :: OSI Approved :: MIT License
Classifier: Operating System :: OS Independent
Requires-Python: >=3.6
License-File: LICENSE.txt
Requires-Dist: volcengine-python-sdk[ark]
Dynamic: license-file
